{
	"configurations" : 
	[
		{
			"directories" : 
			[
				{
					"build" : ".",
					"jsonFile" : "directory-.-Debug-f5ebdc15457944623624.json",
					"minimumCMakeVersion" : 
					{
						"string" : "3.20"
					},
					"projectIndex" : 0,
					"source" : ".",
					"targetIndexes" : 
					[
						0,
						1,
						2,
						3,
						4,
						5
					]
				}
			],
			"name" : "Debug",
			"projects" : 
			[
				{
					"directoryIndexes" : 
					[
						0
					],
					"name" : "ThreadPool",
					"targetIndexes" : 
					[
						0,
						1,
						2,
						3,
						4,
						5
					]
				}
			],
			"targets" : 
			[
				{
					"directoryIndex" : 0,
					"id" : "fiber_test::@6890427a1f51a3e7e1df",
					"jsonFile" : "target-fiber_test-Debug-dfc42cba72e3fb8f0a7a.json",
					"name" : "fiber_test",
					"projectIndex" : 0
				},
				{
					"directoryIndex" : 0,
					"id" : "log_test::@6890427a1f51a3e7e1df",
					"jsonFile" : "target-log_test-Debug-35a9294e271c130fe669.json",
					"name" : "log_test",
					"projectIndex" : 0
				},
				{
					"directoryIndex" : 0,
					"id" : "schedule_test::@6890427a1f51a3e7e1df",
					"jsonFile" : "target-schedule_test-Debug-8360303b561b63116bed.json",
					"name" : "schedule_test",
					"projectIndex" : 0
				},
				{
					"directoryIndex" : 0,
					"id" : "server::@6890427a1f51a3e7e1df",
					"jsonFile" : "target-server-Debug-2194daacae19eed0739f.json",
					"name" : "server",
					"projectIndex" : 0
				},
				{
					"directoryIndex" : 0,
					"id" : "test::@6890427a1f51a3e7e1df",
					"jsonFile" : "target-test-Debug-312c48f156c6d9a2bbde.json",
					"name" : "test",
					"projectIndex" : 0
				},
				{
					"directoryIndex" : 0,
					"id" : "yaml_test::@6890427a1f51a3e7e1df",
					"jsonFile" : "target-yaml_test-Debug-8336a0152aa21e9facee.json",
					"name" : "yaml_test",
					"projectIndex" : 0
				}
			]
		}
	],
	"kind" : "codemodel",
	"paths" : 
	{
		"build" : "/home/xubin/Desktop/WebServer/cmake-build-debug",
		"source" : "/home/xubin/Desktop/WebServer"
	},
	"version" : 
	{
		"major" : 2,
		"minor" : 4
	}
}
